SET.v
module SET ( clk , rst, en, central, radius, mode, busy, valid, candidate );

input clk, rst;
input en;
input [23:0] central;
input [11:0] radius;
input [1:0] mode;
output busy;
output valid;
output [7:0] candidate;

reg busy;
reg valid;
reg [7:0] candidate;

reg [2:0] current_state,next_state;
//state
parameter IDLE = 3'd0;
parameter COMMAND = 3'd1;
parameter OPERATION = 3'd2;
parameter RESULT = 3'd3;

//input data reg 
reg signed [3:0] x1,y1,x2,y2,x3,y3,r1,r2,r3;
reg [1:0] mode_buffer;
always@(posedge clk or posedge rst)
begin
    if(rst) 
    begin
        x1 <= 4'd0;
        y1 <= 4'd0;

        x2 <= 4'd0;
        y2 <= 4'd0;

        x3 <= 4'd0;
        y3 <= 4'd0;

        r1 <= 4'd0;
        r2 <= 4'd0;
        r3 <= 4'd0;
    end
    else if(current_state == COMMAND)
    begin
        x1 = central[23:20];
        y1 = central[19:16];

        x2 = central[15:12];
        y2 = central[11:8];

        x3 = central[7:4];
        y3 = central[3:0];

        r1 <= radius[11:8];
        r2 <= radius[7:4];
        r3 <= radius[3:0];
    end
end

always@(posedge clk or rst)
begin
    if(rst) mode_buffer <= 2'd0;
    else if(current_state == COMMAND) mode_buffer <= mode;
end



reg signed [3:0] x,y;

//state switch
always@(posedge clk or posedge rst)
begin
    if(rst) current_state <= IDLE;
    else current_state <= next_state;
end

//next state logic
always@(*)
begin
    case(current_state)
    IDLE: 
    begin
        if(en) next_state = COMMAND;
        else next_state = IDLE;
    end
    COMMAND:
    begin
        next_state = OPERATION;
    end
    OPERATION:
    begin
        if(x == 4'd8 && y == 4'd8) next_state = RESULT;
        else next_state = OPERATION;
    end
    RESULT:
    begin
        next_state = IDLE;
    end
    default: next_state = IDLE;
    endcase
end

//busy
always@(posedge clk or posedge rst)
begin
    if(rst) busy <= 1'd0;
    else if(next_state == COMMAND && next_state == OPERATION && next_state == RESULT) busy <= 1'd1;
    else busy <= 1'd0;
end

//valid
always@(posedge clk or posedge rst)
begin
    if(rst) valid <= 1'd0;
    else if(next_state == RESULT) valid <= 1'd1;
    else valid <= 1'd0;
end

reg signed [3:0] x_a1,y_b1;
reg signed [8:0] a1,b1; 
reg signed [8:0] r1pow2;
reg signed [8:0] a1_add_b1;
reg yes;
 

always@(*)
begin
    x_a1 = x-x1;
    y_b1 = y-y1;
    a1 = x_a1*x_a1;
    b1 = y_b1*y_b1;
    a1_add_b1 = a1+b1;
    yes = a1_add_b1 <= r1pow2 ;
end

always@(*)
begin
    case(r1)
    4'd0: r1pow2 = 8'd0;
    4'd1: r1pow2 = 8'd1;
    4'd2: r1pow2 = 8'd4;
    4'd3: r1pow2 = 8'd9;
    4'd4: r1pow2 = 8'd16;
    4'd5: r1pow2 = 8'd25;
    4'd6: r1pow2 = 8'd36;
    4'd7: r1pow2 = 8'd49;
    4'd8: r1pow2 = 8'd64;
    default: r1pow2 = 8'd0; 
    endcase
end

//candidate
always@(posedge clk or posedge rst)
begin
    if(rst) candidate <= 8'd0; 
    else if(current_state == OPERATION && mode_buffer == 2'b00)
    begin
        if( yes) candidate <= candidate + 8'd1;
    end
    else if(current_state == RESULT) candidate <= 8'd0;
end

//x y counter
always@(posedge clk or posedge rst)
begin
    if(rst) x <= 4'd1;
    else if(current_state == OPERATION && x == 4'd8) x <= 4'd1;
    else if(current_state == OPERATION) x <= x + 4'd1;
    else if(current_state == RESULT) x <= 4'd1;
end

always@(posedge clk or posedge rst)
begin
    if(rst) y <= 4'd1;
    else if(current_state == OPERATION && x == 4'd8) y <= y + 4'd1;
    else if(current_state == RESULT) y <= 4'd1;
end

endmodule

testfixture.v
`timescale 1ns/10ps
`define SDFFILE    "../SYN/SET_syn.sdf"    // Modify your sdf file name here
`define cycle 10.0
`define terminate_cycle 200000 // Modify your terminate ycle here


module testfixture1;

`define central_pattern "./dat/Central_pattern.dat"
`define radius_pattern "./dat/Radius_pattern.dat"
`define  candidate_result_Length "./dat/candidate_result_Length.dat"
`define  candidate_united_result_Length "./dat/candidate_united_result_Length.dat"
`define  candidate_diff_result_Length "./dat/candidate_diff_result_Length.dat"
`define  candidate_intersect_result_Length "./dat/candidate_intersect_result_Length.dat"

reg clk = 0;
reg rst;
reg en;
reg [23:0] central;
reg [11:0] radius;
reg [1:0] mode;
wire busy;
wire valid;
wire [7:0] candidate;

integer err_cnt;

reg [23:0] central_pat_mem [0:63];
reg [11:0] radius_pat_mem[0:63];
reg [7:0] expected_mem [0:63];

`ifdef SDF
initial $sdf_annotate(`SDFFILE, u_set);
`endif

initial begin
	//$fsdbDumpfile("SET.fsdb");
	//$fsdbDumpvars;
	$dumpfile("SET.vcd");
	$dumpvars;
end

initial begin
	$timeformat(-9, 1, " ns", 9); //Display time in nanoseconds
	$readmemh(`central_pattern, central_pat_mem);
	$readmemh(`radius_pattern, radius_pat_mem);
`ifdef MD1
	$display("--------------------------- [ Function 1. Simulation START !! ] ---------------------------");
	$readmemh(`candidate_result_Length, expected_mem);
`elsif MD2
	$display("--------------------------- [ Function 2. Simulation START !! ] ---------------------------");
	$readmemh(`candidate_united_result_Length, expected_mem);
`elsif MD3
	$display("--------------------------- [ Function 3. Simulation START !! ] ---------------------------");
	$readmemh(`candidate_diff_result_Length, expected_mem);
`elsif MD4
	$display("--------------------------- [ Function 4. Simulation START !! ] ---------------------------");
	$readmemh(`candidate_intersect_result_Length, expected_mem);
`else
	$display("============================================================================");
	$display("|                                                                          |");
	$display("|  Please select one testbench for test !!                                 |");
	$display("|  Simulation can't be initialized !!                                      |");
	$display("|                                                                          |");
	$display("============================================================================");
	#1 $finish;
`endif
end



always #(`cycle/2) clk = ~clk;




initial begin
`ifdef MD1
	mode = 2'b00;
`elsif MD2
	mode = 2'b01;
`elsif MD3
	mode = 2'b10;
`elsif MD4
	mode = 2'b11;
`else
	mode = 2'bx;
`endif
end

SET u_set( .clk(clk), .rst(rst), .en(en), .central(central), .radius(radius), .mode(mode), .busy(busy), .valid(valid), .candidate(candidate) );

integer k;
integer p;
initial begin
	en = 0;
      	rst = 0;
	err_cnt = 0;
# `cycle;     
	rst = 1;
#(`cycle*3);
	rst = 0;
for (k = 0; k<=63; k = k+1) begin
	@(negedge clk);
	//change inputs at strobe point
        #(`cycle/4)	wait(busy == 0);
			en = 1;
			central = central_pat_mem[k];                
      			radius = radius_pat_mem[k];
			#(`cycle) en = 0;
			wait (valid == 1);
          	//Wait for signal output
          	@(negedge clk);
				if (candidate === expected_mem[k])
					$display(" Pattern %d at Mode %d is PASS !", k, mode);
				else begin
					$display(" Pattern %d at Mode %d is FAIL !. Expected candidate = %d, but the Response candidate = %d !! ", k, mode, expected_mem[k], candidate);
					err_cnt = err_cnt + 1;
				end
end
#(`cycle*2); 
     $display("--------------------------- Simulation FINISH !!---------------------------");
     if (err_cnt) begin 
     	$display("============================================================================");
     	$display("\n (T_T) FAIL!! The simulation result is FAIL!!! there were %d errors at all.\n", err_cnt);
	$display("============================================================================");
	end
     else begin 
     	$display("============================================================================");
	$display("\n \\(^o^)/ CONGRATULATIONS!!  The simulation result is PASS!!!\n");
	$display("============================================================================");
	end
$finish;
end


always@(err_cnt) begin
	if (err_cnt == 10) begin
	$display("============================================================================");
     	$display("\n (>_<) FAIL!! The simulation FAIL result is too many ! Please check your code @@ \n");
	$display("============================================================================");
	$finish;
	end
end

initial begin 
	#`terminate_cycle;
	$display("================================================================================================================");
	$display("--------------------------- (/`n`)/ ~#  There was something wrong with your code !! ---------------------------"); 
	$display("--------------------------- The simulation can't finished!!, Please check it !!! ---------------------------"); 
	$display("================================================================================================================");
	$finish;
end


endmodule

SET.vcd
$date
	Sat Aug 29 19:31:33 2020
$end
$version
	Icarus Verilog
$end
$timescale
	10ps
$end
$scope module testfixture1 $end
$var wire 1 ! valid $end
$var wire 8 " candidate [7:0] $end
$var wire 1 # busy $end
$var reg 24 $ central [23:0] $end
$var reg 1 % clk $end
$var reg 1 & en $end
$var reg 2 ' mode [1:0] $end
$var reg 12 ( radius [11:0] $end
$var reg 1 ) rst $end
$var integer 32 * err_cnt [31:0] $end
$var integer 32 + k [31:0] $end
$scope module u_set $end
$var wire 24 , central [23:0] $end
$var wire 1 % clk $end
$var wire 1 & en $end
$var wire 2 - mode [1:0] $end
$var wire 12 . radius [11:0] $end
$var wire 1 ) rst $end
$var reg 9 / a1 [8:0] $end
$var reg 9 0 a1_add_b1 [8:0] $end
$var reg 9 1 b1 [8:0] $end
$var reg 1 # busy $end
$var reg 8 2 candidate [7:0] $end
$var reg 3 3 current_state [2:0] $end
$var reg 2 4 mode_buffer [1:0] $end
$var reg 3 5 next_state [2:0] $end
$var reg 4 6 r1 [3:0] $end
$var reg 9 7 r1pow2 [8:0] $end
$var reg 4 8 r2 [3:0] $end
$var reg 4 9 r3 [3:0] $end
$var reg 1 ! valid $end
$var reg 4 : x [3:0] $end
$var reg 4 ; x1 [3:0] $end
$var reg 4 < x2 [3:0] $end
$var reg 4 = x3 [3:0] $end
$var reg 4 > x_a1 [3:0] $end
$var reg 4 ? y [3:0] $end
$var reg 4 @ y1 [3:0] $end
$var reg 4 A y2 [3:0] $end
$var reg 4 B y3 [3:0] $end
$var reg 4 C y_b1 [3:0] $end
$var reg 1 D yes $end
$upscope $end
$upscope $end
$enddefinitions $end
#0
$dumpvars
xD
bx C
bx B
bx A
bx @
bx ?
bx >
bx =
bx <
bx ;
bx :
bx 9
bx 8
bx 7
bx 6
b0 5
bx 4
bx 3
bx 2
bx 1
bx 0
bx /
bx .
b0 -
bx ,
bx +
b0 *
0)
bx (
b0 '
0&
0%
bx $
x#
bx "
x!
$end
#500
b0 3
0#
0!
1%
#1000
0D
b0 7
b10 0
b1 1
b1 /
b1 C
b1 >
b1 ?
b1 :
b0 "
b0 2
b0 9
b0 8
b0 6
b0 B
b0 =
b0 A
b0 <
b0 @
b0 ;
b0 4
0%
1)
#1500
1%
#2000
0%
#2500
1%
#3000
0%
#3500
1%
#4000
0%
b0 +
0)
#4250
b1 5
b1100110010 (
b1100110010 .
b10101010011001101100010 $
b10101010011001101100010 ,
1&
#4500
b10 5
b1 3
1%
#5000
0%
#5250
0&
#5500
b1001 7
b10 9
b11 8
b11 6
b10 3
b100000 0
b10000 1
b10000 /
b1100 C
b1100 >
b10 B
b110 =
b11 A
b11 <
b101 @
b101 ;
1%
#6000
0%
#6500
b11001 0
b1001 /
b1101 >
b10 :
1%
#7000
0%
#7500
b10100 0
b100 /
b1110 >
b11 :
1%
#8000
0%
#8500
b10001 0
b1 /
b1111 >
b100 :
1%
#9000
0%
#9500
b10000 0
b0 /
b0 >
b101 :
1%
#10000
0%
#10500
b10001 0
b1 /
b1 >
b110 :
1%
#11000
0%
#11500
b10100 0
b100 /
b10 >
b111 :
1%
#12000
0%
#12500
b11001 0
b1001 /
b11 >
b1000 :
1%
#13000
0%
#13500
b1001 1
b10000 /
b1101 C
b1100 >
b1 :
b10 ?
1%
#14000
0%
#14500
b10010 0
b1001 /
b1101 >
b10 :
1%
#15000
0%
#15500
b1101 0
b100 /
b1110 >
b11 :
1%
#16000
0%
#16500
b1010 0
b1 /
b1111 >
b100 :
1%
#17000
0%
#17500
1D
b1001 0
b0 /
b0 >
b101 :
1%
#18000
0%
#18500
0D
b1010 0
b1 /
b1 >
b110 :
b1 "
b1 2
1%
#19000
0%
#19500
b1101 0
b100 /
b10 >
b111 :
1%
#20000
0%
#20500
b10010 0
b1001 /
b11 >
b1000 :
1%
#21000
0%
#21500
b10100 0
b100 1
b10000 /
b1110 C
b1100 >
b1 :
b11 ?
1%
#22000
0%
#22500
b1101 0
b1001 /
b1101 >
b10 :
1%
#23000
0%
#23500
1D
b1000 0
b100 /
b1110 >
b11 :
1%
#24000
0%
#24500
b101 0
b1 /
b1111 >
b100 :
b10 "
b10 2
1%
#25000
0%
#25500
b100 0
b0 /
b0 >
b11 "
b11 2
b101 :
1%
#26000
0%
#26500
b101 0
b1 /
b1 >
b110 :
b100 "
b100 2
1%
#27000
0%
#27500
b1000 0
b100 /
b10 >
b101 "
b101 2
b111 :
1%
#28000
0%
#28500
0D
b1101 0
b1001 /
b11 >
b1000 :
b110 "
b110 2
1%
#29000
0%
#29500
b10001 0
b1 1
b10000 /
b1111 C
b1100 >
b1 :
b100 ?
1%
#30000
0%
#30500
b1010 0
b1001 /
b1101 >
b10 :
1%
#31000
0%
#31500
1D
b101 0
b100 /
b1110 >
b11 :
1%
#32000
0%
#32500
b10 0
b1 /
b1111 >
b100 :
b111 "
b111 2
1%
#33000
0%
#33500
b1 0
b0 /
b0 >
b1000 "
b1000 2
b101 :
1%
#34000
0%
#34500
b10 0
b1 /
b1 >
b110 :
b1001 "
b1001 2
1%
#35000
0%
#35500
b101 0
b100 /
b10 >
b1010 "
b1010 2
b111 :
1%
#36000
0%
#36500
0D
b1010 0
b1001 /
b11 >
b1000 :
b1011 "
b1011 2
1%
#37000
0%
#37500
b10000 0
b0 1
b10000 /
b0 C
b1100 >
b1 :
b101 ?
1%
#38000
0%
#38500
1D
b1001 0
b1001 /
b1101 >
b10 :
1%
#39000
0%
#39500
b100 0
b100 /
b1110 >
b1100 "
b1100 2
b11 :
1%
#40000
0%
#40500
b1 0
b1 /
b1111 >
b100 :
b1101 "
b1101 2
1%
#41000
0%
#41500
b0 0
b0 /
b0 >
b1110 "
b1110 2
b101 :
1%
#42000
0%
#42500
b1 0
b1 /
b1 >
b110 :
b1111 "
b1111 2
1%
#43000
0%
#43500
b100 0
b100 /
b10 >
b10000 "
b10000 2
b111 :
1%
#44000
0%
#44500
b1001 0
b1001 /
b11 >
b1000 :
b10001 "
b10001 2
1%
#45000
0%
#45500
0D
b10001 0
b1 1
b10000 /
b1 C
b1100 >
b10010 "
b10010 2
b1 :
b110 ?
1%
#46000
0%
#46500
b1010 0
b1001 /
b1101 >
b10 :
1%
#47000
0%
#47500
1D
b101 0
b100 /
b1110 >
b11 :
1%
#48000
0%
#48500
b10 0
b1 /
b1111 >
b100 :
b10011 "
b10011 2
1%
#49000
0%
#49500
b1 0
b0 /
b0 >
b10100 "
b10100 2
b101 :
1%
#50000
0%
#50500
b10 0
b1 /
b1 >
b110 :
b10101 "
b10101 2
1%
#51000
0%
#51500
b101 0
b100 /
b10 >
b10110 "
b10110 2
b111 :
1%
#52000
0%
#52500
0D
b1010 0
b1001 /
b11 >
b1000 :
b10111 "
b10111 2
1%
#53000
0%
#53500
b10100 0
b100 1
b10000 /
b10 C
b1100 >
b1 :
b111 ?
1%
#54000
0%
#54500
b1101 0
b1001 /
b1101 >
b10 :
1%
#55000
0%
#55500
1D
b1000 0
b100 /
b1110 >
b11 :
1%
#56000
0%
#56500
b101 0
b1 /
b1111 >
b100 :
b11000 "
b11000 2
1%
#57000
0%
#57500
b100 0
b0 /
b0 >
b11001 "
b11001 2
b101 :
1%
#58000
0%
#58500
b101 0
b1 /
b1 >
b110 :
b11010 "
b11010 2
1%
#59000
0%
#59500
b1000 0
b100 /
b10 >
b11011 "
b11011 2
b111 :
1%
#60000
0%
#60500
0D
b1101 0
b1001 /
b11 >
b1000 :
b11100 "
b11100 2
1%
#61000
0%
#61500
b11001 0
b1001 1
b10000 /
b11 C
b1100 >
b1 :
b1000 ?
1%
#62000
0%
#62500
b10010 0
b1001 /
b1101 >
b10 :
1%
#63000
0%
#63500
b1101 0
b100 /
b1110 >
b11 :
1%
#64000
0%
#64500
b1010 0
b1 /
b1111 >
b100 :
1%
#65000
0%
#65500
1D
b1001 0
b0 /
b0 >
b101 :
1%
#66000
0%
#66500
0D
b1010 0
b1 /
b1 >
b110 :
b11101 "
b11101 2
1%
#67000
0%
#67500
b1101 0
b100 /
b10 >
b111 :
1%
#68000
0%
#68500
b10010 0
b1001 /
b11 >
b11 5
b1000 :
1%
#69000
0%
#69500
b100000 0
b10000 1
b10000 /
b100 C
b1100 >
b0 5
b11 3
1!
b1 :
b1001 ?
1%
#70000
b1 +
0%
#70500
b1100 C
b1 ?
b0 "
b0 2
0!
b0 3
1%
#71000
0%
#71250
b1 5
b1000100011 (
b1000100011 .
b10001100010010001010011 $
b10001100010010001010011 ,
1&
#71500
b10 5
b1 3
1%
#72000
0%
#72250
0&
#72500
b100 7
b10 3
b11 9
b10 8
b10 6
b100010 0
b11001 1
b1001 /
b1011 C
b1101 >
b11 B
b101 =
b100 A
b10 <
b110 @
b100 ;
1%
#73000
0%
#73500
b11101 0
b100 /
b1110 >
b10 :
1%
#74000
0%
#74500
b11010 0
b1 /
b1111 >
b11 :
1%
#75000
0%
#75500
b11001 0
b0 /
b0 >
b100 :
1%
#76000
0%
#76500
b11010 0
b1 /
b1 >
b101 :
1%
#77000
0%
#77500
b11101 0
b100 /
b10 >
b110 :
1%
#78000
0%
#78500
b100010 0
b1001 /
b11 >
b111 :
1%
#79000
0%
#79500
b101001 0
b10000 /
b100 >
b1000 :
1%
#80000
0%
#80500
b11001 0
b10000 1
b1001 /
b1100 C
b1101 >
b10 ?
b1 :
1%
#81000
0%
#81500
b10100 0
b100 /
b1110 >
b10 :
1%
#82000
0%
#82500
b10001 0
b1 /
b1111 >
b11 :
1%
#83000
0%
#83500
b10000 0
b0 /
b0 >
b100 :
1%
#84000
0%
#84500
b10001 0
b1 /
b1 >
b101 :
1%
#85000
0%
#85500
b10100 0
b100 /
b10 >
b110 :
1%
#86000
0%
#86500
b11001 0
b1001 /
b11 >
b111 :
1%
#87000
0%
#87500
b100000 0
b10000 /
b100 >
b1000 :
1%
#88000
0%
#88500
b10010 0
b1001 1
b1001 /
b1101 C
b1101 >
b11 ?
b1 :
1%
#89000
0%
#89500
b1101 0
b100 /
b1110 >
b10 :
1%
#90000
0%
#90500
b1010 0
b1 /
b1111 >
b11 :
1%
#91000
0%
#91500
b1001 0
b0 /
b0 >
b100 :
1%
#92000
0%
#92500
b1010 0
b1 /
b1 >
b101 :
1%
#93000
0%
#93500
b1101 0
b100 /
b10 >
b110 :
1%
#94000
0%
#94500
b10010 0
b1001 /
b11 >
b111 :
1%
#95000
0%
#95500
b11001 0
b10000 /
b100 >
b1000 :
1%
#96000
0%
#96500
b1101 0
b100 1
b1001 /
b1110 C
b1101 >
b100 ?
b1 :
1%
#97000
0%
#97500
b1000 0
b100 /
b1110 >
b10 :
1%
#98000
0%
#98500
b101 0
b1 /
b1111 >
b11 :
1%
#99000
0%
#99500
1D
b100 0
b0 /
b0 >
b100 :
1%
#100000
0%
#100500
0D
b101 0
b1 /
b1 >
b101 :
b1 "
b1 2
1%
#101000
0%
#101500
b1000 0
b100 /
b10 >
b110 :
1%
#102000
0%
#102500
b1101 0
b1001 /
b11 >
b111 :
1%
#103000
0%
#103500
b10100 0
b10000 /
b100 >
b1000 :
1%
#104000
0%
#104500
b1010 0
b1 1
b1001 /
b1111 C
b1101 >
b101 ?
b1 :
1%
#105000
0%
#105500
b101 0
b100 /
b1110 >
b10 :
1%
#106000
0%
#106500
1D
b10 0
b1 /
b1111 >
b11 :
1%
#107000
0%
#107500
b1 0
b0 /
b0 >
b10 "
b10 2
b100 :
1%
#108000
0%
#108500
b10 0
b1 /
b1 >
b101 :
b11 "
b11 2
1%
#109000
0%
#109500
0D
b101 0
b100 /
b10 >
b100 "
b100 2
b110 :
1%
#110000
0%
#110500
b1010 0
b1001 /
b11 >
b111 :
1%
#111000
0%
#111500
b10001 0
b10000 /
b100 >
b1000 :
1%
#112000
0%
#112500
b1001 0
b0 1
b1001 /
b0 C
b1101 >
b110 ?
b1 :
1%
#113000
0%
#113500
1D
b100 0
b100 /
b1110 >
b10 :
1%
#114000
0%
#114500
b1 0
b1 /
b1111 >
b11 :
b101 "
b101 2
1%
#115000
0%
#115500
b0 0
b0 /
b0 >
b110 "
b110 2
b100 :
1%
#116000
0%
#116500
b1 0
b1 /
b1 >
b101 :
b111 "
b111 2
1%
#117000
0%
#117500
b100 0
b100 /
b10 >
b1000 "
b1000 2
b110 :
1%
#118000
0%
#118500
0D
b1001 0
b1001 /
b11 >
b111 :
b1001 "
b1001 2
1%
#119000
0%
#119500
b10000 0
b10000 /
b100 >
b1000 :
1%
#120000
0%
#120500
b1010 0
b1 1
b1001 /
b1 C
b1101 >
b111 ?
b1 :
1%
#121000
0%
#121500
b101 0
b100 /
b1110 >
b10 :
1%
#122000
0%
#122500
1D
b10 0
b1 /
b1111 >
b11 :
1%
#123000
0%
#123500
b1 0
b0 /
b0 >
b1010 "
b1010 2
b100 :
1%
#124000
0%
#124500
b10 0
b1 /
b1 >
b101 :
b1011 "
b1011 2
1%
#125000
0%
#125500
0D
b101 0
b100 /
b10 >
b1100 "
b1100 2
b110 :
1%
#126000
0%
#126500
b1010 0
b1001 /
b11 >
b111 :
1%
#127000
0%
#127500
b10001 0
b10000 /
b100 >
b1000 :
1%
#128000
0%
#128500
b1101 0
b100 1
b1001 /
b10 C
b1101 >
b1000 ?
b1 :
1%
#129000
0%
#129500
b1000 0
b100 /
b1110 >
b10 :
1%
#130000
0%
#130500
b101 0
b1 /
b1111 >
b11 :
1%
#131000
0%
#131500
1D
b100 0
b0 /
b0 >
b100 :
1%
#132000
0%
#132500
0D
b101 0
b1 /
b1 >
b101 :
b1101 "
b1101 2
1%
#133000
0%
#133500
b1000 0
b100 /
b10 >
b110 :
1%
#134000
0%
#134500
b1101 0
b1001 /
b11 >
b111 :
1%
#135000
0%
#135500
b10100 0
b10000 /
b100 >
b11 5
b1000 :
1%
#136000
0%
#136500
b10010 0
b1001 1
b1001 /
b11 C
b1101 >
b0 5
b1001 ?
b1 :
1!
b11 3
1%
#137000
b10 +
0%
#137500
b100010 0
b11001 1
b1011 C
b0 3
0!
b0 "
b0 2
b1 ?
1%
#138000
0%
#138250
b1 5
b11101100001011001000010 $
b11101100001011001000010 ,
1&
#138500
b10 5
b1 3
1%
#139000
0%
#139250
0&
#139500
b10 3
b111101 0
b100100 /
b1010 >
b10 B
b100 =
b110 A
b1 <
b111 ;
1%
#140000
0%
#140500
b110010 0
b11001 /
b1011 >
b10 :
1%
#141000
0%
#141500
b101001 0
b10000 /
b1100 >
b11 :
1%
#142000
0%
#142500
b100010 0
b1001 /
b1101 >
b100 :
1%
#143000
0%
#143500
b11101 0
b100 /
b1110 >
b101 :
1%
#144000
0%
#144500
b11010 0
b1 /
b1111 >
b110 :
1%
#145000
0%
#145500
b11001 0
b0 /
b0 >
b111 :
1%
#146000
0%
#146500
b11010 0
b1 /
b1 >
b1000 :
1%
#147000
0%
#147500
b110100 0
b10000 1
b100100 /
b1100 C
b1010 >
b1 :
b10 ?
1%
#148000
0%
#148500
b101001 0
b11001 /
b1011 >
b10 :
1%
#149000
0%
#149500
b100000 0
b10000 /
b1100 >
b11 :
1%
#150000
0%
#150500
b11001 0
b1001 /
b1101 >
b100 :
1%
#151000
0%
#151500
b10100 0
b100 /
b1110 >
b101 :
1%
#152000
0%
#152500
b10001 0
b1 /
b1111 >
b110 :
1%
#153000
0%
#153500
b10000 0
b0 /
b0 >
b111 :
1%
#154000
0%
#154500
b10001 0
b1 /
b1 >
b1000 :
1%
#155000
0%
#155500
b101101 0
b1001 1
b100100 /
b1101 C
b1010 >
b1 :
b11 ?
1%
#156000
0%
#156500
b100010 0
b11001 /
b1011 >
b10 :
1%
#157000
0%
#157500
b11001 0
b10000 /
b1100 >
b11 :
1%
#158000
0%
#158500
b10010 0
b1001 /
b1101 >
b100 :
1%
#159000
0%
#159500
b1101 0
b100 /
b1110 >
b101 :
1%
#160000
0%
#160500
b1010 0
b1 /
b1111 >
b110 :
1%
#161000
0%
#161500
b1001 0
b0 /
b0 >
b111 :
1%
#162000
0%
#162500
b1010 0
b1 /
b1 >
b1000 :
1%
#163000
0%
#163500
b101000 0
b100 1
b100100 /
b1110 C
b1010 >
b1 :
b100 ?
1%
#164000
0%
#164500
b11101 0
b11001 /
b1011 >
b10 :
1%
#165000
0%
#165500
b10100 0
b10000 /
b1100 >
b11 :
1%
#166000
0%
#166500
b1101 0
b1001 /
b1101 >
b100 :
1%
#167000
0%
#167500
b1000 0
b100 /
b1110 >
b101 :
1%
#168000
0%
#168500
b101 0
b1 /
b1111 >
b110 :
1%
#169000
0%
#169500
1D
b100 0
b0 /
b0 >
b111 :
1%
#170000
0%
#170500
0D
b101 0
b1 /
b1 >
b1000 :
b1 "
b1 2
1%
#171000
0%
#171500
b100101 0
b1 1
b100100 /
b1111 C
b1010 >
b1 :
b101 ?
1%
#172000
0%
#172500
b11010 0
b11001 /
b1011 >
b10 :
1%
#173000
0%
#173500
b10001 0
b10000 /
b1100 >
b11 :
1%
#174000
0%
#174500
b1010 0
b1001 /
b1101 >
b100 :
1%
#175000
0%
#175500
b101 0
b100 /
b1110 >
b101 :
1%
#176000
0%
#176500
1D
b10 0
b1 /
b1111 >
b110 :
1%
#177000
0%
#177500
b1 0
b0 /
b0 >
b10 "
b10 2
b111 :
1%
#178000
0%
#178500
b10 0
b1 /
b1 >
b1000 :
b11 "
b11 2
1%
#179000
0%
#179500
0D
b100100 0
b0 1
b100100 /
b0 C
b1010 >
b100 "
b100 2
b1 :
b110 ?
1%
#180000
0%
#180500
b11001 0
b11001 /
b1011 >
b10 :
1%
#181000
0%
#181500
b10000 0
b10000 /
b1100 >
b11 :
1%
#182000
0%
#182500
b1001 0
b1001 /
b1101 >
b100 :
1%
#183000
0%
#183500
1D
b100 0
b100 /
b1110 >
b101 :
1%
#184000
0%
#184500
b1 0
b1 /
b1111 >
b110 :
b101 "
b101 2
1%
#185000
0%
#185500
b0 0
b0 /
b0 >
b110 "
b110 2
b111 :
1%
#186000
0%
#186500
b1 0
b1 /
b1 >
b1000 :
b111 "
b111 2
1%
#187000
0%
#187500
0D
b100101 0
b1 1
b100100 /
b1 C
b1010 >
b1000 "
b1000 2
b1 :
b111 ?
1%
#188000
0%
#188500
b11010 0
b11001 /
b1011 >
b10 :
1%
#189000
0%
#189500
b10001 0
b10000 /
b1100 >
b11 :
1%
#190000
0%
#190500
b1010 0
b1001 /
b1101 >
b100 :
1%
#191000
0%
#191500
b101 0
b100 /
b1110 >
b101 :
1%
#192000
0%
#192500
1D
b10 0
b1 /
b1111 >
b110 :
1%
#193000
0%
#193500
b1 0
b0 /
b0 >
b1001 "
b1001 2
b111 :
1%
#194000
0%
#194500
b10 0
b1 /
b1 >
b1000 :
b1010 "
b1010 2
1%
#195000
0%
#195500
0D
b101000 0
b100 1
b100100 /
b10 C
b1010 >
b1011 "
b1011 2
b1 :
b1000 ?
1%
#196000
0%
#196500
b11101 0
b11001 /
b1011 >
b10 :
1%
#197000
0%
#197500
b10100 0
b10000 /
b1100 >
b11 :
1%
#198000
0%
#198500
b1101 0
b1001 /
b1101 >
b100 :
1%
#199000
0%
#199500
b1000 0
b100 /
b1110 >
b101 :
1%
#200000
0%
#200500
b101 0
b1 /
b1111 >
b110 :
1%
#201000
0%
#201500
1D
b100 0
b0 /
b0 >
b111 :
1%
#202000
0%
#202500
0D
b101 0
b1 /
b1 >
b11 5
b1000 :
b1100 "
b1100 2
1%
#203000
0%
#203500
b101101 0
b1001 1
b100100 /
b11 C
b1010 >
b0 5
b11 3
1!
b1 :
b1001 ?
1%
#204000
b11 +
0%
#204500
b111101 0
b11001 1
b1011 C
b1 ?
b0 "
b0 2
0!
b0 3
1%
#205000
0%
#205250
b1 5
b1100100010 (
b1100100010 .
b11000111001001001100110 $
b11000111001001001100110 ,
1&
#205500
b10 5
b1 3
1%
#206000
0%
#206250
0&
#206500
b1001 7
b10 3
b10 9
b11 6
b11101 0
b100 1
b11001 /
b1110 C
b1011 >
b110 B
b110 =
b10 A
b1001 <
b11 @
b110 ;
1%
#207000
0%
#207500
b10100 0
b10000 /
b1100 >
b10 :
1%
#208000
0%
#208500
b1101 0
b1001 /
b1101 >
b11 :
1%
#209000
0%
#209500
1D
b1000 0
b100 /
b1110 >
b100 :
1%
#210000
0%
#210500
b101 0
b1 /
b1111 >
b101 :
b1 "
b1 2
1%
#211000
0%
#211500
b100 0
b0 /
b0 >
b10 "
b10 2
b110 :
1%
#212000
0%
#212500
b101 0
b1 /
b1 >
b111 :
b11 "
b11 2
1%
#213000
0%
#213500
b1000 0
b100 /
b10 >
b100 "
b100 2
b1000 :
1%
#214000
0%
#214500
0D
b11010 0
b1 1
b11001 /
b1111 C
b1011 >
b10 ?
b1 :
b101 "
b101 2
1%
#215000
0%
#215500
b10001 0
b10000 /
b1100 >
b10 :
1%
#216000
0%
#216500
b1010 0
b1001 /
b1101 >
b11 :
1%
#217000
0%
#217500
1D
b101 0
b100 /
b1110 >
b100 :
1%
#218000
0%
#218500
b10 0
b1 /
b1111 >
b101 :
b110 "
b110 2
1%
#219000
0%
#219500
b1 0
b0 /
b0 >
b111 "
b111 2
b110 :
1%
#220000
0%
#220500
b10 0
b1 /
b1 >
b111 :
b1000 "
b1000 2
1%
#221000
0%
#221500
b101 0
b100 /
b10 >
b1001 "
b1001 2
b1000 :
1%
#222000
0%
#222500
0D
b11001 0
b0 1
b11001 /
b0 C
b1011 >
b11 ?
b1 :
b1010 "
b1010 2
1%
#223000
0%
#223500
b10000 0
b10000 /
b1100 >
b10 :
1%
#224000
0%
#224500
1D
b1001 0
b1001 /
b1101 >
b11 :
1%
#225000
0%
#225500
b100 0
b100 /
b1110 >
b1011 "
b1011 2
b100 :
1%
#226000
0%
#226500
b1 0
b1 /
b1111 >
b101 :
b1100 "
b1100 2
1%
#227000
0%
#227500
b0 0
b0 /
b0 >
b1101 "
b1101 2
b110 :
1%
#228000
0%
#228500
b1 0
b1 /
b1 >
b111 :
b1110 "
b1110 2
1%
#229000
0%
#229500
b100 0
b100 /
b10 >
b1111 "
b1111 2
b1000 :
1%
#230000
0%
#230500
0D
b11010 0
b1 1
b11001 /
b1 C
b1011 >
b100 ?
b1 :
b10000 "
b10000 2
1%
