SET.v
module SET ( clk , rst, en, central, radius, mode, busy, valid, candidate );

input clk, rst;
input en;
input [23:0] central;
input [11:0] radius;
input [1:0] mode;
output busy;
output valid;
output [7:0] candidate;

reg busy;
reg valid;
reg [7:0] candidate;

reg [2:0] current_state,next_state;
//state
parameter IDLE = 3'd0;
parameter COMMAND = 3'd1;
parameter OPERATION = 3'd2;
parameter RESULT = 3'd3;

//input data reg 
reg signed [3:0] x1,y1,x2,y2,x3,y3,r1,r2,r3;
reg [1:0] mode_buffer;
always@(posedge clk or posedge rst)
begin
    if(rst) 
    begin
        x1 <= 4'd0;
        y1 <= 4'd0;

        x2 <= 4'd0;
        y2 <= 4'd0;

        x3 <= 4'd0;
        y3 <= 4'd0;

        r1 <= 4'd0;
        r2 <= 4'd0;
        r3 <= 4'd0;
    end
    else if(current_state == COMMAND)
    begin
        x1 = central[23:20];
        y1 = central[19:16];

        x2 = central[15:12];
        y2 = central[11:8];

        x3 = central[7:4];
        y3 = central[3:0];

        r1 <= radius[11:8];
        r2 <= radius[7:4];
        r3 <= radius[3:0];
    end
end

always@(posedge clk or rst)
begin
    if(rst) mode_buffer <= 2'd0;
    else if(current_state == COMMAND) mode_buffer <= mode;
end



reg signed [3:0] x,y;

//state switch
always@(posedge clk or posedge rst)
begin
    if(rst) current_state <= IDLE;
    else current_state <= next_state;
end

//next state logic
always@(*)
begin
    case(current_state)
    IDLE: 
    begin
        if(en) next_state = COMMAND;
        else next_state = IDLE;
    end
    COMMAND:
    begin
        next_state = OPERATION;
    end
    OPERATION:
    begin
        if(x == 4'd8 && y == 4'd8) next_state = RESULT;
        else next_state = OPERATION;
    end
    RESULT:
    begin
        next_state = IDLE;
    end
    default: next_state = IDLE;
    endcase
end

//busy
always@(posedge clk or posedge rst)
begin
    if(rst) busy <= 1'd0;
    else if(next_state == COMMAND && next_state == OPERATION && next_state == RESULT) busy <= 1'd1;
    else busy <= 1'd0;
end

//valid
always@(posedge clk or posedge rst)
begin
    if(rst) valid <= 1'd0;
    else if(next_state == RESULT) valid <= 1'd1;
    else valid <= 1'd0;
end

reg signed [3:0] x_a1,y_b1;
reg signed [8:0] a1,b1; 
reg signed [8:0] r1pow2;
reg signed [8:0] a1_add_b1;
reg union_A;

reg signed [3:0] x_a2,y_b2;
reg signed [8:0] a2,b2;
reg signed [8:0] r2pow2;
reg signed [8:0] a2_add_b2;
reg union_B;

reg signed [3:0] x_a3,y_b3;
reg signed [8:0] a3,b3;
reg signed [8:0] r3pow2;
reg signed [8:0] a3_add_b3;
reg union_C;

always@(*)
begin
    x_a1 = x-x1;
    y_b1 = y-y1;
    a1 = x_a1*x_a1;
    b1 = y_b1*y_b1;
    a1_add_b1 = a1+b1;
    union_A = a1_add_b1 <= r1pow2 ;
end

always@(*)
begin
    x_a2 = x-x2;
    y_b2 = y-y2;
    a2 = x_a2*x_a2;
    b2 = y_b2*y_b2;
    a2_add_b2 = a2+b2;
    union_B = a2_add_b2 <= r2pow2 ;
end

always@(*)
begin
    x_a3 = x-x3;
    y_b3 = y-y3;
    a3 = x_a3*x_a3;
    b3 = y_b3*y_b3;
    a3_add_b3 = a3+b3;
    union_C = a3_add_b3 <= r3pow2 ;
end


always@(*)
begin
    case(r1)
    4'd0: r1pow2 = 8'd0;
    4'd1: r1pow2 = 8'd1;
    4'd2: r1pow2 = 8'd4;
    4'd3: r1pow2 = 8'd9;
    4'd4: r1pow2 = 8'd16;
    4'd5: r1pow2 = 8'd25;
    4'd6: r1pow2 = 8'd36;
    4'd7: r1pow2 = 8'd49;
    4'd8: r1pow2 = 8'd64;
    default: r1pow2 = 8'd0; 
    endcase
end

always@(*)
begin
    case(r2)
    4'd0: r2pow2 = 8'd0;
    4'd1: r2pow2 = 8'd1;
    4'd2: r2pow2 = 8'd4;
    4'd3: r2pow2 = 8'd9;
    4'd4: r2pow2 = 8'd16;
    4'd5: r2pow2 = 8'd25;
    4'd6: r2pow2 = 8'd36;
    4'd7: r2pow2 = 8'd49;
    4'd8: r2pow2 = 8'd64;
    default: r2pow2 = 8'd0; 
    endcase
end

always@(*)
begin
    case(r3)
    4'd0: r3pow2 = 8'd0;
    4'd1: r3pow2 = 8'd1;
    4'd2: r3pow2 = 8'd4;
    4'd3: r3pow2 = 8'd9;
    4'd4: r3pow2 = 8'd16;
    4'd5: r3pow2 = 8'd25;
    4'd6: r3pow2 = 8'd36;
    4'd7: r3pow2 = 8'd49;
    4'd8: r3pow2 = 8'd64;
    default: r3pow2 = 8'd0; 
    endcase
end

//candidate
always@(posedge clk or posedge rst)
begin
    if(rst) candidate <= 8'd0; 
    else if(current_state == OPERATION && mode_buffer == 2'b00)
    begin
        if(union_A) candidate <= candidate + 8'd1;
    end
    else if(current_state == OPERATION && mode_buffer == 2'b01)
    begin
        if(union_A && union_B) candidate <= candidate + 8'd1;
    end
    else if(current_state == OPERATION && mode_buffer == 2'b10)
    begin
        if( (union_A && !union_B) || (!union_A && union_B)) candidate <= candidate + 8'd1;
    end
    else if(current_state == OPERATION && mode_buffer == 2'b11)
    begin
        if( !(union_A && union_B && union_C) )
        begin
            if( (union_A && union_B) || (union_B && union_C) || (union_C && union_A))
            begin
                candidate <= candidate + 8'd1;
            end
        end
    end
    else if(current_state == RESULT) candidate <= 8'd0;
end

//x y counter
always@(posedge clk or posedge rst)
begin
    if(rst) x <= 4'd1;
    else if(current_state == OPERATION && x == 4'd8) x <= 4'd1;
    else if(current_state == OPERATION) x <= x + 4'd1;
    else if(current_state == RESULT) x <= 4'd1;
end

always@(posedge clk or posedge rst)
begin
    if(rst) y <= 4'd1;
    else if(current_state == OPERATION && x == 4'd8) y <= y + 4'd1;
    else if(current_state == RESULT) y <= 4'd1;
end

endmodule

testfixture.v
`timescale 1ns/10ps
`define SDFFILE    "../SYN/SET_syn.sdf"    // Modify your sdf file name here
`define cycle 10.0
`define terminate_cycle 200000 // Modify your terminate ycle here


module testfixture1;

`define central_pattern "./dat/Central_pattern.dat"
`define radius_pattern "./dat/Radius_pattern.dat"
`define  candidate_result_Length "./dat/candidate_result_Length.dat"
`define  candidate_united_result_Length "./dat/candidate_united_result_Length.dat"
`define  candidate_diff_result_Length "./dat/candidate_diff_result_Length.dat"
`define  candidate_intersect_result_Length "./dat/candidate_intersect_result_Length.dat"

reg clk = 0;
reg rst;
reg en;
reg [23:0] central;
reg [11:0] radius;
reg [1:0] mode;
wire busy;
wire valid;
wire [7:0] candidate;

integer err_cnt;

reg [23:0] central_pat_mem [0:63];
reg [11:0] radius_pat_mem[0:63];
reg [7:0] expected_mem [0:63];

`ifdef SDF
initial $sdf_annotate(`SDFFILE, u_set);
`endif

initial begin
	//$fsdbDumpfile("SET.fsdb");
	//$fsdbDumpvars;
	$dumpfile("SET.vcd");
	$dumpvars;
end

initial begin
	$timeformat(-9, 1, " ns", 9); //Display time in nanoseconds
	$readmemh(`central_pattern, central_pat_mem);
	$readmemh(`radius_pattern, radius_pat_mem);
`ifdef MD1
	$display("--------------------------- [ Function 1. Simulation START !! ] ---------------------------");
	$readmemh(`candidate_result_Length, expected_mem);
`elsif MD2
	$display("--------------------------- [ Function 2. Simulation START !! ] ---------------------------");
	$readmemh(`candidate_united_result_Length, expected_mem);
`elsif MD3
	$display("--------------------------- [ Function 3. Simulation START !! ] ---------------------------");
	$readmemh(`candidate_diff_result_Length, expected_mem);
`elsif MD4
	$display("--------------------------- [ Function 4. Simulation START !! ] ---------------------------");
	$readmemh(`candidate_intersect_result_Length, expected_mem);
`else
	$display("============================================================================");
	$display("|                                                                          |");
	$display("|  Please select one testbench for test !!                                 |");
	$display("|  Simulation can't be initialized !!                                      |");
	$display("|                                                                          |");
	$display("============================================================================");
	#1 $finish;
`endif
end



always #(`cycle/2) clk = ~clk;




initial begin
`ifdef MD1
	mode = 2'b00;
`elsif MD2
	mode = 2'b01;
`elsif MD3
	mode = 2'b10;
`elsif MD4
	mode = 2'b11;
`else
	mode = 2'bx;
`endif
end

SET u_set( .clk(clk), .rst(rst), .en(en), .central(central), .radius(radius), .mode(mode), .busy(busy), .valid(valid), .candidate(candidate) );

integer k;
integer p;
initial begin
	en = 0;
      	rst = 0;
	err_cnt = 0;
# `cycle;     
	rst = 1;
#(`cycle*3);
	rst = 0;
for (k = 0; k<=63; k = k+1) begin
	@(negedge clk);
	//change inputs at strobe point
        #(`cycle/4)	wait(busy == 0);
			en = 1;
			central = central_pat_mem[k];                
      			radius = radius_pat_mem[k];
			#(`cycle) en = 0;
			wait (valid == 1);
          	//Wait for signal output
          	@(negedge clk);
				if (candidate === expected_mem[k])
					$display(" Pattern %d at Mode %d is PASS !", k, mode);
				else begin
					$display(" Pattern %d at Mode %d is FAIL !. Expected candidate = %d, but the Response candidate = %d !! ", k, mode, expected_mem[k], candidate);
					err_cnt = err_cnt + 1;
				end
end
#(`cycle*2); 
     $display("--------------------------- Simulation FINISH !!---------------------------");
     if (err_cnt) begin 
     	$display("============================================================================");
     	$display("\n (T_T) FAIL!! The simulation result is FAIL!!! there were %d errors at all.\n", err_cnt);
	$display("============================================================================");
	end
     else begin 
     	$display("============================================================================");
	$display("\n \\(^o^)/ CONGRATULATIONS!!  The simulation result is PASS!!!\n");
	$display("============================================================================");
	end
$finish;
end


always@(err_cnt) begin
	if (err_cnt == 10) begin
	$display("============================================================================");
     	$display("\n (>_<) FAIL!! The simulation FAIL result is too many ! Please check your code @@ \n");
	$display("============================================================================");
	$finish;
	end
end

initial begin 
	#`terminate_cycle;
	$display("================================================================================================================");
	$display("--------------------------- (/`n`)/ ~#  There was something wrong with your code !! ---------------------------"); 
	$display("--------------------------- The simulation can't finished!!, Please check it !!! ---------------------------"); 
	$display("================================================================================================================");
	$finish;
end


endmodule

SET.vcd
$date
	Sat Aug 29 19:43:55 2020
$end
$version
	Icarus Verilog
$end
$timescale
	10ps
$end
$scope module testfixture1 $end
$var wire 1 ! valid $end
$var wire 8 " candidate [7:0] $end
$var wire 1 # busy $end
$var reg 24 $ central [23:0] $end
$var reg 1 % clk $end
$var reg 1 & en $end
$var reg 2 ' mode [1:0] $end
$var reg 12 ( radius [11:0] $end
$var reg 1 ) rst $end
$var integer 32 * err_cnt [31:0] $end
$var integer 32 + k [31:0] $end
$scope module u_set $end
$var wire 24 , central [23:0] $end
$var wire 1 % clk $end
$var wire 1 & en $end
$var wire 2 - mode [1:0] $end
$var wire 12 . radius [11:0] $end
$var wire 1 ) rst $end
$var reg 9 / a1 [8:0] $end
$var reg 9 0 a1_add_b1 [8:0] $end
$var reg 9 1 a2 [8:0] $end
$var reg 9 2 a2_add_b2 [8:0] $end
$var reg 9 3 a3 [8:0] $end
$var reg 9 4 a3_add_b3 [8:0] $end
$var reg 9 5 b1 [8:0] $end
$var reg 9 6 b2 [8:0] $end
$var reg 9 7 b3 [8:0] $end
$var reg 1 # busy $end
$var reg 8 8 candidate [7:0] $end
$var reg 3 9 current_state [2:0] $end
$var reg 2 : mode_buffer [1:0] $end
$var reg 3 ; next_state [2:0] $end
$var reg 4 < r1 [3:0] $end
$var reg 9 = r1pow2 [8:0] $end
$var reg 4 > r2 [3:0] $end
$var reg 9 ? r2pow2 [8:0] $end
$var reg 4 @ r3 [3:0] $end
$var reg 9 A r3pow2 [8:0] $end
$var reg 1 B union_A $end
$var reg 1 C union_B $end
$var reg 1 D union_C $end
$var reg 1 ! valid $end
$var reg 4 E x [3:0] $end
$var reg 4 F x1 [3:0] $end
$var reg 4 G x2 [3:0] $end
$var reg 4 H x3 [3:0] $end
$var reg 4 I x_a1 [3:0] $end
$var reg 4 J x_a2 [3:0] $end
$var reg 4 K x_a3 [3:0] $end
$var reg 4 L y [3:0] $end
$var reg 4 M y1 [3:0] $end
$var reg 4 N y2 [3:0] $end
$var reg 4 O y3 [3:0] $end
$var reg 4 P y_b1 [3:0] $end
$var reg 4 Q y_b2 [3:0] $end
$var reg 4 R y_b3 [3:0] $end
$upscope $end
$upscope $end
$enddefinitions $end
#0
$dumpvars
bx R
bx Q
bx P
bx O
bx N
bx M
bx L
bx K
bx J
bx I
bx H
bx G
bx F
bx E
xD
xC
xB
bx A
bx @
bx ?
bx >
bx =
bx <
b0 ;
bx :
bx 9
bx 8
bx 7
bx 6
bx 5
bx 4
bx 3
bx 2
bx 1
bx 0
bx /
bx .
b11 -
bx ,
bx +
b0 *
0)
bx (
b11 '
0&
0%
bx $
x#
bx "
x!
$end
#500
b0 9
0#
0!
1%
#1000
0D
0C
0B
b0 A
b0 ?
b0 =
b10 4
b1 7
b1 3
b1 R
b1 K
b10 2
b1 6
b1 1
b1 Q
b1 J
b10 0
b1 5
b1 /
b1 P
b1 I
b1 L
b1 E
b0 "
b0 8
b0 @
b0 >
b0 <
b0 O
b0 H
b0 N
b0 G
b0 M
b0 F
b0 :
0%
1)
#1500
1%
#2000
0%
#2500
1%
#3000
0%
#3500
1%
#4000
0%
b0 +
0)
#4250
b1 ;
b1100110010 (
b1100110010 .
b10101010011001101100010 $
b10101010011001101100010 ,
1&
#4500
b10 ;
b1 9
1%
#5000
0%
#5250
0&
#5500
1C
b100 A
b1001 ?
b1001 =
b10 @
b11 >
b11 <
b10 9
b11 :
b11010 4
b11001 3
b1111 R
b1011 K
b1000 2
b100 6
b100 1
b1110 Q
b1110 J
b100000 0
b10000 5
b10000 /
b1100 P
b1100 I
b10 O
b110 H
b11 N
b11 G
b101 M
b101 F
1%
#6000
0%
#6500
b10001 4
b10000 3
b1100 K
b101 2
b1 1
b1111 J
b11001 0
b1001 /
b1101 I
b10 E
1%
#7000
0%
#7500
b1010 4
b1001 3
b1101 K
b100 2
b0 1
b0 J
b10100 0
b100 /
b1110 I
b11 E
1%
#8000
0%
#8500
b101 4
b100 3
b1110 K
b101 2
b1 1
b1 J
b10001 0
b1 /
b1111 I
b100 E
1%
#9000
0%
#9500
1D
b10 4
b1 3
b1111 K
b1000 2
b100 1
b10 J
b10000 0
b0 /
b0 I
b101 E
1%
#10000
0%
#10500
b1 4
b0 3
b0 K
0C
b1101 2
b1001 1
b11 J
b10001 0
b1 /
b1 I
b110 E
b1 "
b1 8
1%
#11000
0%
#11500
b10 4
b1 3
b1 K
b10100 2
b10000 1
b100 J
b10100 0
b100 /
b10 I
b111 E
1%
#12000
0%
#12500
0D
b101 4
b100 3
b10 K
b11101 2
b11001 1
b101 J
b11001 0
b1001 /
b11 I
b1000 E
1%
#13000
0%
#13500
b11001 4
b0 7
b11001 3
b0 R
b1011 K
1C
b101 2
b1 6
b100 1
b1111 Q
b1110 J
b1001 5
b10000 /
b1101 P
b1100 I
b1 E
b10 L
1%
#14000
0%
#14500
b10000 4
b10000 3
b1100 K
b10 2
b1 1
b1111 J
b10010 0
b1001 /
b1101 I
b10 E
1%
#15000
0%
#15500
b1001 4
b1001 3
b1101 K
b1 2
b0 1
b0 J
b1101 0
b100 /
b1110 I
b11 E
1%
#16000
0%
#16500
1D
b100 4
b100 3
b1110 K
b10 2
b1 1
b1 J
b1010 0
b1 /
b1111 I
b100 E
1%
#17000
0%
#17500
b1 4
b1 3
b1111 K
b101 2
b100 1
b10 J
1B
b1001 0
b0 /
b0 I
b10 "
b10 8
b101 E
1%
#18000
0%
#18500
b0 4
b0 3
b0 K
0C
b1010 2
b1001 1
b11 J
0B
b1010 0
b1 /
b1 I
b110 E
1%
#19000
0%
#19500
b1 4
b1 3
b1 K
b10001 2
b10000 1
b100 J
b1101 0
b100 /
b10 I
b111 E
1%
#20000
0%
#20500
b100 4
b100 3
b10 K
b11010 2
b11001 1
b101 J
b10010 0
b1001 /
b11 I
b1000 E
1%
#21000
0%
#21500
0D
b11010 4
b1 7
b11001 3
b1 R
b1011 K
1C
b100 2
b0 6
b100 1
b0 Q
b1110 J
b10100 0
b100 5
b10000 /
b1110 P
b1100 I
b1 E
b11 L
1%
#22000
0%
#22500
b10001 4
b10000 3
b1100 K
b1 2
b1 1
b1111 J
b1101 0
b1001 /
b1101 I
b10 E
1%
#23000
0%
#23500
b1010 4
b1001 3
b1101 K
b0 2
b0 1
b0 J
1B
b1000 0
b100 /
b1110 I
b11 E
1%
#24000
0%
#24500
b101 4
b100 3
b1110 K
b1 2
b1 1
b1 J
b101 0
b1 /
b1111 I
b100 E
b11 "
b11 8
1%
#25000
0%
#25500
1D
b10 4
b1 3
b1111 K
b100 2
b100 1
b10 J
b100 0
b0 /
b0 I
b100 "
b100 8
b101 E
1%
#26000
0%
#26500
b1 4
b0 3
b0 K
b1001 2
b1001 1
b11 J
b101 0
b1 /
b1 I
b110 E
1%
#27000
0%
#27500
b10 4
b1 3
b1 K
0C
b10000 2
b10000 1
b100 J
b1000 0
b100 /
b10 I
b111 E
1%
#28000
0%
#28500
0D
b101 4
b100 3
b10 K
b11001 2
b11001 1
b101 J
0B
b1101 0
b1001 /
b11 I
b1000 E
b101 "
b101 8
1%
#29000
0%
#29500
b11101 4
b100 7
b11001 3
b10 R
b1011 K
1C
b101 2
b1 6
b100 1
b1 Q
b1110 J
b10001 0
b1 5
b10000 /
b1111 P
b1100 I
b1 E
b100 L
1%
#30000
0%
#30500
b10100 4
b10000 3
b1100 K
b10 2
b1 1
b1111 J
b1010 0
b1001 /
b1101 I
b10 E
1%
#31000
0%
#31500
b1101 4
b1001 3
b1101 K
b1 2
b0 1
b0 J
1B
b101 0
b100 /
b1110 I
b11 E
1%
#32000
0%
#32500
b1000 4
b100 3
b1110 K
b10 2
b1 1
b1 J
b10 0
b1 /
b1111 I
b100 E
b110 "
b110 8
1%
#33000
0%
#33500
b101 4
b1 3
b1111 K
b101 2
b100 1
b10 J
b1 0
b0 /
b0 I
b111 "
b111 8
b101 E
1%
#34000
0%
#34500
1D
b100 4
b0 3
b0 K
0C
b1010 2
b1001 1
b11 J
b10 0
b1 /
b1 I
b110 E
b1000 "
b1000 8
1%
#35000
0%
#35500
0D
b101 4
b1 3
b1 K
b10001 2
b10000 1
b100 J
b101 0
b100 /
b10 I
b1001 "
b1001 8
b111 E
1%
#36000
0%
#36500
b1000 4
b100 3
b10 K
b11010 2
b11001 1
b101 J
0B
b1010 0
b1001 /
b11 I
b1000 E
1%
#37000
0%
#37500
b100010 4
b1001 7
b11001 3
b11 R
b1011 K
1C
b1000 2
b100 6
b100 1
b10 Q
b1110 J
b10000 0
b0 5
b10000 /
b0 P
b1100 I
b1 E
b101 L
1%
#38000
0%
#38500
b11001 4
b10000 3
b1100 K
b101 2
b1 1
b1111 J
1B
b1001 0
b1001 /
b1101 I
b10 E
1%
#39000
0%
#39500
b10010 4
b1001 3
b1101 K
b100 2
b0 1
b0 J
b100 0
b100 /
b1110 I
b1010 "
b1010 8
b11 E
1%
#40000
0%
#40500
b1101 4
b100 3
b1110 K
b101 2
b1 1
b1 J
b1 0
b1 /
b1111 I
b100 E
b1011 "
b1011 8
1%
#41000
0%
#41500
b1010 4
b1 3
b1111 K
b1000 2
b100 1
b10 J
b0 0
b0 /
b0 I
b1100 "
b1100 8
b101 E
1%
#42000
0%
#42500
b1001 4
b0 3
b0 K
0C
b1101 2
b1001 1
b11 J
b1 0
b1 /
b1 I
b110 E
b1101 "
b1101 8
1%
#43000
0%
#43500
b1010 4
b1 3
b1 K
b10100 2
b10000 1
b100 J
b100 0
b100 /
b10 I
b111 E
1%
#44000
0%
#44500
b1101 4
b100 3
b10 K
b11101 2
b11001 1
b101 J
b1001 0
b1001 /
b11 I
b1000 E
1%
#45000
0%
#45500
b101001 4
b10000 7
b11001 3
b100 R
b1011 K
b1101 2
b1001 6
b100 1
b11 Q
b1110 J
0B
b10001 0
b1 5
b10000 /
b1 P
b1100 I
b1 E
b110 L
1%
#46000
0%
#46500
b100000 4
b10000 3
b1100 K
b1010 2
b1 1
b1111 J
b1010 0
b1001 /
b1101 I
b10 E
1%
#47000
0%
#47500
b11001 4
b1001 3
b1101 K
1C
b1001 2
b0 1
b0 J
1B
b101 0
b100 /
b1110 I
b11 E
1%
#48000
0%
#48500
b10100 4
b100 3
b1110 K
0C
b1010 2
b1 1
b1 J
b10 0
b1 /
b1111 I
b100 E
b1110 "
b1110 8
1%
#49000
0%
#49500
b10001 4
b1 3
b1111 K
b1101 2
b100 1
b10 J
b1 0
b0 /
b0 I
b101 E
1%
#50000
0%
#50500
b10000 4
b0 3
b0 K
b10010 2
b1001 1
b11 J
b10 0
b1 /
b1 I
b110 E
1%
#51000
0%
#51500
b10001 4
b1 3
b1 K
b11001 2
b10000 1
b100 J
b101 0
b100 /
b10 I
b111 E
1%
#52000
0%
#52500
b10100 4
b100 3
b10 K
b100010 2
b11001 1
b101 J
0B
b1010 0
b1001 /
b11 I
b1000 E
1%
#53000
0%
#53500
b110010 4
b11001 7
b11001 3
b101 R
b1011 K
b10100 2
b10000 6
b100 1
b100 Q
b1110 J
b10100 0
b100 5
b10000 /
b10 P
b1100 I
b1 E
b111 L
1%
#54000
0%
#54500
b101001 4
b10000 3
b1100 K
b10001 2
b1 1
b1111 J
b1101 0
b1001 /
b1101 I
b10 E
1%
#55000
0%
#55500
b100010 4
b1001 3
b1101 K
b10000 2
b0 1
b0 J
1B
b1000 0
b100 /
b1110 I
b11 E
1%
#56000
0%
#56500
b11101 4
b100 3
b1110 K
b10001 2
b1 1
b1 J
b101 0
b1 /
b1111 I
b100 E
1%
#57000
0%
#57500
b11010 4
b1 3
b1111 K
b10100 2
b100 1
b10 J
b100 0
b0 /
b0 I
b101 E
1%
#58000
0%
#58500
b11001 4
b0 3
b0 K
b11001 2
b1001 1
b11 J
b101 0
b1 /
b1 I
b110 E
1%
#59000
0%
#59500
b11010 4
b1 3
b1 K
b100000 2
b10000 1
b100 J
b1000 0
b100 /
b10 I
b111 E
1%
#60000
0%
#60500
b11101 4
b100 3
b10 K
b101001 2
b11001 1
b101 J
0B
b1101 0
b1001 /
b11 I
b1000 E
1%
#61000
0%
#61500
b111101 4
b100100 7
b11001 3
b110 R
b1011 K
b11101 2
b11001 6
b100 1
b101 Q
b1110 J
b11001 0
b1001 5
b10000 /
b11 P
b1100 I
b1 E
b1000 L
1%
#62000
0%
#62500
b110100 4
b10000 3
b1100 K
b11010 2
b1 1
b1111 J
b10010 0
b1001 /
b1101 I
b10 E
1%
#63000
0%
#63500
b101101 4
b1001 3
b1101 K
b11001 2
b0 1
b0 J
b1101 0
b100 /
b1110 I
b11 E
1%
#64000
0%
#64500
b101000 4
b100 3
b1110 K
b11010 2
b1 1
b1 J
b1010 0
b1 /
b1111 I
b100 E
1%
#65000
0%
#65500
b100101 4
b1 3
b1111 K
b11101 2
b100 1
b10 J
1B
b1001 0
b0 /
b0 I
b101 E
1%
#66000
0%
#66500
b100100 4
b0 3
b0 K
b100010 2
b1001 1
b11 J
0B
b1010 0
b1 /
b1 I
b110 E
1%
#67000
0%
#67500
b100101 4
b1 3
b1 K
b101001 2
b10000 1
b100 J
b1101 0
b100 /
b10 I
b111 E
1%
#68000
0%
#68500
b101000 4
b100 3
b10 K
b110010 2
b11001 1
b101 J
b10010 0
b1001 /
b11 I
b11 ;
b1000 E
1%
#69000
0%
#69500
b1001010 4
b110001 7
b11001 3
b111 R
b1011 K
b101000 2
b100100 6
b100 1
b110 Q
b1110 J
b100000 0
b10000 5
b10000 /
b100 P
b1100 I
b0 ;
b11 9
1!
b1 E
b1001 L
1%
#70000
b1 +
0%
#70500
b11010 4
b1 7
b1111 R
1C
b1000 2
b100 6
b1110 Q
b1100 P
b1 L
b0 "
b0 8
0!
b0 9
1%
#71000
0%
#71250
b1 ;
b1000100011 (
b1000100011 .
b10001100010010001010011 $
b10001100010010001010011 ,
1&
#71500
b10 ;
b1 9
1%
#72000
0%
#72250
0&
#72500
b1001 A
b100 ?
b100 =
b10 9
b11 @
b10 >
b10 <
b10100 4
b100 7
b10000 3
b1110 R
b1100 K
0C
b1010 2
b1001 6
b1 1
b1101 Q
b1111 J
b100010 0
b11001 5
b1001 /
b1011 P
b1101 I
b11 O
b101 H
b100 N
b10 G
b110 M
b100 F
1%
#73000
0%
#73500
b1101 4
b1001 3
b1101 K
b1001 2
b0 1
b0 J
b11101 0
b100 /
b1110 I
b10 E
1%
#74000
0%
#74500
1D
b1000 4
b100 3
b1110 K
b1010 2
b1 1
b1 J
b11010 0
b1 /
b1111 I
b11 E
1%
#75000
0%
#75500
b101 4
b1 3
b1111 K
b1101 2
b100 1
b10 J
b11001 0
b0 /
b0 I
b100 E
1%
#76000
0%
#76500
b100 4
b0 3
b0 K
b10010 2
b1001 1
b11 J
b11010 0
b1 /
b1 I
b101 E
1%
#77000
0%
#77500
b101 4
b1 3
b1 K
b11001 2
b10000 1
b100 J
b11101 0
b100 /
b10 I
b110 E
1%
#78000
0%
#78500
b1000 4
b100 3
b10 K
b100010 2
b11001 1
b101 J
b100010 0
b1001 /
b11 I
b111 E
1%
#79000
0%
#79500
0D
b1101 4
b1001 3
b11 K
b101101 2
b100100 1
b110 J
b101001 0
b10000 /
b100 I
b1000 E
1%
#80000
0%
#80500
b10001 4
b1 7
b10000 3
b1111 R
b1100 K
b101 2
b100 6
b1 1
b1110 Q
b1111 J
b11001 0
b10000 5
b1001 /
b1100 P
b1101 I
b10 L
b1 E
1%
#81000
0%
#81500
b1010 4
b1001 3
b1101 K
1C
b100 2
b0 1
b0 J
b10100 0
b100 /
b1110 I
b10 E
1%
#82000
0%
#82500
1D
b101 4
b100 3
b1110 K
0C
b101 2
b1 1
b1 J
b10001 0
b1 /
b1111 I
b11 E
1%
#83000
0%
#83500
b10 4
b1 3
b1111 K
b1000 2
b100 1
b10 J
b10000 0
b0 /
b0 I
b100 E
1%
#84000
0%
#84500
b1 4
b0 3
b0 K
b1101 2
b1001 1
b11 J
b10001 0
b1 /
b1 I
b101 E
1%
#85000
0%
#85500
b10 4
b1 3
b1 K
b10100 2
b10000 1
b100 J
b10100 0
b100 /
b10 I
b110 E
1%
#86000
0%
#86500
b101 4
b100 3
b10 K
b11101 2
b11001 1
b101 J
b11001 0
b1001 /
b11 I
b111 E
1%
#87000
0%
#87500
0D
b1010 4
b1001 3
b11 K
b101000 2
b100100 1
b110 J
b100000 0
b10000 /
b100 I
b1000 E
1%
#88000
0%
#88500
b10000 4
b0 7
b10000 3
b0 R
b1100 K
1C
b10 2
b1 6
b1 1
b1111 Q
b1111 J
b10010 0
b1001 5
b1001 /
b1101 P
b1101 I
b11 L
b1 E
1%
#89000
0%
#89500
1D
b1001 4
b1001 3
b1101 K
b1 2
b0 1
b0 J
b1101 0
b100 /
b1110 I
b10 E
1%
#90000
0%
#90500
b100 4
b100 3
b1110 K
b10 2
b1 1
b1 J
b1010 0
b1 /
b1111 I
b11 E
b1 "
b1 8
1%
#91000
0%
#91500
b1 4
b1 3
b1111 K
0C
b101 2
b100 1
b10 J
b1001 0
b0 /
b0 I
b10 "
b10 8
b100 E
1%
#92000
0%
#92500
b0 4
b0 3
b0 K
b1010 2
b1001 1
b11 J
b1010 0
b1 /
b1 I
b101 E
1%
#93000
0%
#93500
b1 4
b1 3
b1 K
b10001 2
b10000 1
b100 J
b1101 0
b100 /
b10 I
b110 E
1%
#94000
0%
#94500
b100 4
b100 3
b10 K
b11010 2
b11001 1
b101 J
b10010 0
b1001 /
b11 I
b111 E
1%
#95000
0%
#95500
b1001 4
b1001 3
b11 K
b100101 2
b100100 1
b110 J
b11001 0
b10000 /
b100 I
b1000 E
1%
#96000
0%
#96500
0D
b10001 4
b1 7
b10000 3
b1 R
b1100 K
1C
b1 2
b0 6
b1 1
b0 Q
b1111 J
b1101 0
b100 5
b1001 /
b1110 P
b1101 I
b100 L
b1 E
1%
#97000
0%
#97500
b1010 4
b1001 3
b1101 K
b0 2
b0 1
b0 J
b1000 0
b100 /
b1110 I
b10 E
1%
#98000
0%
#98500
1D
b101 4
b100 3
b1110 K
b1 2
b1 1
b1 J
b101 0
b1 /
b1111 I
b11 E
1%
#99000
0%
#99500
b10 4
b1 3
b1111 K
b100 2
b100 1
b10 J
1B
b100 0
b0 /
b0 I
b11 "
b11 8
b100 E
1%
#100000
0%
#100500
b1 4
b0 3
b0 K
0C
b1001 2
b1001 1
b11 J
0B
b101 0
b1 /
b1 I
b101 E
1%
#101000
0%
#101500
b10 4
b1 3
b1 K
b10000 2
b10000 1
b100 J
b1000 0
b100 /
b10 I
b110 E
1%
#102000
0%
#102500
b101 4
b100 3
b10 K
b11001 2
b11001 1
b101 J
b1101 0
b1001 /
b11 I
b111 E
1%
#103000
0%
#103500
0D
b1010 4
b1001 3
b11 K
b100100 2
b100100 1
b110 J
b10100 0
b10000 /
b100 I
b1000 E
1%
#104000
0%
#104500
b10100 4
b100 7
b10000 3
b10 R
b1100 K
1C
b10 2
b1 6
b1 1
b1 Q
b1111 J
b1010 0
b1 5
b1001 /
b1111 P
b1101 I
b101 L
b1 E
1%
#105000
0%
#105500
b1101 4
b1001 3
b1101 K
b1 2
b0 1
b0 J
b101 0
b100 /
b1110 I
b10 E
1%
#106000
0%
#106500
1D
b1000 4
b100 3
b1110 K
b10 2
b1 1
b1 J
1B
b10 0
b1 /
b1111 I
b11 E
1%
#107000
0%
#107500
b101 4
b1 3
b1111 K
0C
b101 2
b100 1
b10 J
b1 0
b0 /
b0 I
b100 E
1%
#108000
0%
#108500
b100 4
b0 3
b0 K
b1010 2
b1001 1
b11 J
b10 0
b1 /
b1 I
b101 E
b100 "
b100 8
1%
#109000
0%
#109500
b101 4
b1 3
b1 K
b10001 2
b10000 1
b100 J
0B
b101 0
b100 /
b10 I
b101 "
b101 8
b110 E
1%
#110000
0%
#110500
b1000 4
b100 3
b10 K
b11010 2
b11001 1
b101 J
b1010 0
b1001 /
b11 I
b111 E
1%
#111000
0%
#111500
0D
b1101 4
b1001 3
b11 K
b100101 2
b100100 1
b110 J
b10001 0
b10000 /
b100 I
b1000 E
1%
#112000
0%
